tabkit/__init__.py
tabkit/config.py
tabkit/data/__init__.py
tabkit/data/column_metadata.py
tabkit/data/compute_bins.py
tabkit/data/data_config.py
tabkit/data/table_processor.py
tabkit/data/transforms.py
tabkit/data/utils/__init__.py
tabkit/data/utils/load_from_disk.py
tabkit/data/utils/load_openml_dataset.py
tabkit/data/utils/load_uci_dataset.py
tabkit/data/utils/pick_label_col.py
tabkit/utils/__init__.py
tabkit/utils/configuration.py
tabkit/utils/logger.py
tabkit/utils/random_id.py
tabkit/utils/slugify.py
table_toolkit-2025.11.9.dist-info/METADATA
table_toolkit-2025.11.9.dist-info/WHEEL
table_toolkit-2025.11.9.dist-info/RECORD
