Metadata-Version: 2.4
Name: table-toolkit
Version: 2025.11.9
Summary: A Python library for consistent preprocessing of tabular data with automatic type inference, caching, and stratified splitting
Project-URL: Homepage, https://github.com/inwonakng/tabkit
Project-URL: Repository, https://github.com/inwonakng/tabkit
Project-URL: Issues, https://github.com/inwonakng/tabkit/issues
Author-email: inwonakng <inwon.kang04@gmail.com>
License: MIT
Keywords: data-processing,machine-learning,pandas,preprocessing,sklearn,tabular
Classifier: Development Status :: 3 - Alpha
Classifier: Intended Audience :: Developers
Classifier: Intended Audience :: Science/Research
Classifier: License :: OSI Approved :: MIT License
Classifier: Programming Language :: Python :: 3
Classifier: Programming Language :: Python :: 3.10
Classifier: Programming Language :: Python :: 3.11
Classifier: Programming Language :: Python :: 3.12
Classifier: Topic :: Scientific/Engineering
Classifier: Topic :: Software Development :: Libraries :: Python Modules
Requires-Python: >=3.10
Requires-Dist: liac-arff<3,>=2.5.0
Requires-Dist: numpy<3,>=2.2.6
Requires-Dist: openml<0.16,>=0.15.1
Requires-Dist: pandas<3,>=2.3.2
Requires-Dist: pyyaml<7,>=6.0.2
Requires-Dist: scikit-learn<2,>=1.3.0
Requires-Dist: ucimlrepo<0.0.8,>=0.0.7
Provides-Extra: dev
Requires-Dist: build<2,>=1.3.0; extra == 'dev'
Requires-Dist: pytest-mock<4,>=3.14.1; extra == 'dev'
Requires-Dist: pytest<9,>=8.4.1; extra == 'dev'
Requires-Dist: twine<7,>=6.1.0; extra == 'dev'
